{
    "model": {
        "type": "range_dispatch",
        "property": "custom_model_data",
        "entries": [
            {
                "threshold": 18001,
                "model": {
                    "type": "model",
                    "model": "magic:icons/spells/stash"
                }
            },
            {
                "threshold": 18002,
                "model": {
                    "type": "model",
                    "model": "magic:icons_disabled/spells/stash"
                }
            },
            {
                "threshold": 19001,
                "model": {
                    "type": "model",
                    "model": "magic:icons_enabled/spells/stash"
                }
            }
        ],
        "fallback": {
            "type": "model",
            "model": "item/ender_chest"
        }
    }
}